{
  "notes": [
    {
      "name": "sd",
      "surname": "Defsmsdsd",
      "phone": "+ssd",
      "id": 1
    },
    {
      "name": "Def",
      "surname": "Ay",
      "phone": "+79680782298213",
      "id": 2
    },
    {
      "name": "Travis",
      "surname": "Scott",
      "phone": "21212121",
      "id": 3
    },
    {
      "name": "Savage",
      "surname": "Molone",
      "phone": "89898",
      "id": 4
    },
    {
      "name": "Айхан",
      "surname": "Аскерзаде",
      "phone": "89252085158",
      "id": 5
    }
  ],
  "comments": [
    {
      "id": 1,
      "body": "апап"
    }
  ],
  "profile": {
    "name": "typicode"
  }
}